{"cameraMode":{"drawMode":2,"name":"Shaded Wireframe","section":"Shading Mode"},"sceneLighting":false,"audioPlay":false,"sceneViewState":{"showFog":true,"showMaterialUpdate":false,"showSkybox":false,"showFlares":true,"showImageEffects":true,"showParticleSystems":true},"in2DMode":false,"pivot":{"x":0.59521484375,"y":13.235595703125,"z":2.5126953125},"rotation":{"x":0.0623747892677784,"y":-0.9168305397033691,"z":0.1583242267370224,"w":0.36120256781578066},"size":7.286242961883545,"orthographic":true}